How2jJavaChujijiaocheng/README.md
How2jJavaChujijiaocheng/__init__.py
How2jJavaChujijiaocheng/__main__.py
How2jJavaChujijiaocheng/file.epub
How2jJavaChujijiaocheng/index.html
How2jJavaChujijiaocheng/css/__init__.py
How2jJavaChujijiaocheng/css/annotations.css
How2jJavaChujijiaocheng/css/main.css
How2jJavaChujijiaocheng/css/normalize.css
How2jJavaChujijiaocheng/css/popup.css
How2jJavaChujijiaocheng/font/__init__.py
How2jJavaChujijiaocheng/font/fontello.eot
How2jJavaChujijiaocheng/font/fontello.svg
How2jJavaChujijiaocheng/font/fontello.ttf
How2jJavaChujijiaocheng/font/fontello.woff
How2jJavaChujijiaocheng/img/__init__.py
How2jJavaChujijiaocheng/img/annotator-glyph-sprite.png
How2jJavaChujijiaocheng/img/annotator-icon-sprite.png
How2jJavaChujijiaocheng/img/apple-touch-icon.png
How2jJavaChujijiaocheng/img/cancelfullscreen.png
How2jJavaChujijiaocheng/img/close.png
How2jJavaChujijiaocheng/img/fullscreen.png
How2jJavaChujijiaocheng/img/loader.gif
How2jJavaChujijiaocheng/img/menu-icon.png
How2jJavaChujijiaocheng/img/save.png
How2jJavaChujijiaocheng/img/saved.png
How2jJavaChujijiaocheng/img/settings-s.png
How2jJavaChujijiaocheng/img/settings.png
How2jJavaChujijiaocheng/img/star.png
How2jJavaChujijiaocheng/js/__init__.py
How2jJavaChujijiaocheng/js/epub.js
How2jJavaChujijiaocheng/js/epub.min.js
How2jJavaChujijiaocheng/js/epub.min.map
How2jJavaChujijiaocheng/js/hooks.min.js
How2jJavaChujijiaocheng/js/hooks.min.map
How2jJavaChujijiaocheng/js/reader.js
How2jJavaChujijiaocheng/js/reader.js.map
How2jJavaChujijiaocheng/js/reader.min.js
How2jJavaChujijiaocheng/js/reader.min.map
How2jJavaChujijiaocheng/js/hooks/__init__.py
How2jJavaChujijiaocheng/js/hooks/extensions/__init__.py
How2jJavaChujijiaocheng/js/hooks/extensions/highlight.js
How2jJavaChujijiaocheng/js/libs/__init__.py
How2jJavaChujijiaocheng/js/libs/jquery.min.js
How2jJavaChujijiaocheng/js/libs/localforage.min.js
How2jJavaChujijiaocheng/js/libs/screenfull.js
How2jJavaChujijiaocheng/js/libs/screenfull.min.js
how2j_java_chujijiaocheng-2024.3.5.0.dist-info/METADATA
how2j_java_chujijiaocheng-2024.3.5.0.dist-info/WHEEL
how2j_java_chujijiaocheng-2024.3.5.0.dist-info/entry_points.txt
how2j_java_chujijiaocheng-2024.3.5.0.dist-info/top_level.txt
how2j_java_chujijiaocheng-2024.3.5.0.dist-info/RECORD
